mjooln/__init__.py
mjooln/core/__init__.py
mjooln/core/glass.py
mjooln/core/seed.py
mjooln/core/serializable.py
mjooln/encryption/__init__.py
mjooln/encryption/crypt.py
mjooln/environment/__init__.py
mjooln/environment/environment.py
mjooln/exception/__init__.py
mjooln/exception/exception.py
mjooln/filesystem/__init__.py
mjooln/filesystem/archive.py
mjooln/filesystem/file.py
mjooln/filesystem/folder.py
mjooln/filesystem/path.py
mjooln/filesystem/serializer.py
mjooln/primitives/__init__.py
mjooln/primitives/atom.py
mjooln/primitives/atoms.py
mjooln/primitives/identity.py
mjooln/primitives/key.py
mjooln/primitives/keys.py
mjooln/primitives/word.py
mjooln/primitives/zulu.py
mjooln/py.typed
mjooln/utils/__init__.py
mjooln/utils/math.py
mjooln/utils/text.py
mjooln/utils/tic.py
mjooln/utils/waiter.py
mjooln-0.10.1.dist-info/WHEEL
mjooln-0.10.1.dist-info/METADATA
mjooln-0.10.1.dist-info/RECORD
