Metadata-Version: 2.3
Name: mjooln
Version: 0.10.1
Summary: Local File handling for Data Engineers
Keywords: json,path,file,folder,file handling,encryption,compression,aes,gzip,uuid,utc,data engineer,data lake,microservice
Author: Vemund Halmø Aarstrand
Author-email: Vemund Halmø Aarstrand <vemundaa@gmail.com>
License: MIT
Requires-Dist: cryptography>=46.0.3
Requires-Dist: python-dateutil>=2.9.0.post0
Requires-Dist: pytz>=2025.2
Requires-Dist: pyyaml>=6.0.3
Requires-Dist: simplejson>=3.20.2
Requires-Python: >=3.11
